{
  "writtings": [
    {
      "date": "2012-01-01T00:00:00Z",
      "id": "2012-01-douai-notre-ville-monique-amghar"
    },
    {
      "date": "2012-12-01T00:00:00Z",
      "id": "2012-12-douai-notre-ville-monique-amghar"
    }
  ],
  "sentences": [
    {
      "date": "2012-01-01T00:00:00Z",
      "count": 11
    },
    {
      "date": "2012-12-01T00:00:00Z",
      "count": 14
    }
  ],
  "sentiments": [
    {
      "date": "2012-01-01T00:00:00Z",
      "positive": 0,
      "neutral": 11,
      "negative": 0
    },
    {
      "date": "2012-12-01T00:00:00Z",
      "positive": 1,
      "neutral": 12,
      "negative": 1
    }
  ],
  "exclamations": [
    {
      "date": "2012-01-01T00:00:00Z",
      "count": 2
    },
    {
      "date": "2012-12-01T00:00:00Z",
      "count": 3
    }
  ],
  "questions": [
    {
      "date": "2012-01-01T00:00:00Z",
      "count": 1
    },
    {
      "date": "2012-12-01T00:00:00Z",
      "count": 0
    }
  ],
  "bolds": [
    {
      "date": "2012-01-01T00:00:00Z",
      "count": 1
    },
    {
      "date": "2012-12-01T00:00:00Z",
      "count": 1
    }
  ],
  "caps": [
    {
      "date": "2012-01-01T00:00:00Z",
      "count": 0
    },
    {
      "date": "2012-12-01T00:00:00Z",
      "count": 1
    }
  ],
  "words": [
    {
      "word": "année",
      "count": 6
    },
    {
      "word": "politique",
      "count": 5
    },
    {
      "word": "maire",
      "count": 4
    },
    {
      "word": "commercial",
      "count": 4
    },
    {
      "word": "successeur",
      "count": 4
    },
    {
      "word": "place",
      "count": 4
    },
    {
      "word": "devoir",
      "count": 2
    },
    {
      "word": "repenser",
      "count": 2
    },
    {
      "word": "circulation",
      "count": 2
    },
    {
      "word": "stationnement",
      "count": 2
    },
    {
      "word": "ville",
      "count": 2
    },
    {
      "word": "souhaiter",
      "count": 2
    },
    {
      "word": "dire",
      "count": 2
    },
    {
      "word": "attendre",
      "count": 2
    },
    {
      "word": "piéton",
      "count": 2
    },
    {
      "word": "rendre",
      "count": 2
    },
    {
      "word": "participatif",
      "count": 2
    },
    {
      "word": "débat",
      "count": 2
    },
    {
      "word": "p.i.c",
      "count": 1
    },
    {
      "word": "collégramme",
      "count": 1
    },
    {
      "word": "magnifique",
      "count": 1
    },
    {
      "word": "voilà",
      "count": 1
    },
    {
      "word": "terme",
      "count": 1
    },
    {
      "word": "dithyrambique",
      "count": 1
    },
    {
      "word": "exprimer",
      "count": 1
    }
  ],
  "portrait": "default.svg",
  "name": "Monique AMGHAR",
  "mandates": [
    "Conseillère municipale d’opposition"
  ],
  "groups": [
    "Élus d’opposition : Vivons Douai (Parti Socialiste)"
  ],
  "groupsIds": [
    "vivons-douai-ps"
  ],
  "locality": "Douai",
  "country": "France",
  "summary": {
    "sentences": {
      "mean": 12.5,
      "min": 11,
      "max": 14
    },
    "exclamations": {
      "mean": 2.5,
      "min": 2,
      "max": 3
    },
    "questions": {
      "mean": 0.5,
      "min": 0,
      "max": 1
    },
    "bolds": {
      "mean": 1,
      "min": 1,
      "max": 1
    },
    "caps": {
      "mean": 0.5,
      "min": 0,
      "max": 1
    },
    "sentiments": {
      "positive": {
        "mean": 0.5,
        "min": 0,
        "max": 1
      },
      "neutral": {
        "mean": 11.5,
        "min": 11,
        "max": 12
      },
      "negative": {
        "mean": 0.5,
        "min": 0,
        "max": 1
      }
    }
  }
}