{
  "writtings": [
    {
      "date": "2020-11-01T00:00:00Z",
      "id": "2020-11-douai-notre-ville-virginie-malolepszy"
    }
  ],
  "sentences": [
    {
      "date": "2020-11-01T00:00:00Z",
      "count": 7
    }
  ],
  "sentiments": [
    {
      "date": "2020-11-01T00:00:00Z",
      "positive": 1,
      "neutral": 6,
      "negative": 0
    }
  ],
  "exclamations": [
    {
      "date": "2020-11-01T00:00:00Z",
      "count": 1
    }
  ],
  "questions": [
    {
      "date": "2020-11-01T00:00:00Z",
      "count": 0
    }
  ],
  "bolds": [
    {
      "date": "2020-11-01T00:00:00Z",
      "count": 0
    }
  ],
  "caps": [
    {
      "date": "2020-11-01T00:00:00Z",
      "count": 0
    }
  ],
  "words": [
    {
      "word": "long",
      "count": 1
    },
    {
      "word": "toucher",
      "count": 1
    },
    {
      "word": "crise",
      "count": 1
    },
    {
      "word": "sanitaire",
      "count": 1
    },
    {
      "word": "impact",
      "count": 1
    },
    {
      "word": "commerçant",
      "count": 1
    },
    {
      "word": "indépendant",
      "count": 1
    },
    {
      "word": "artisan",
      "count": 1
    },
    {
      "word": "restaurateur",
      "count": 1
    },
    {
      "word": "cafetier",
      "count": 1
    },
    {
      "word": "faire",
      "count": 1
    },
    {
      "word": "preuve",
      "count": 1
    },
    {
      "word": "initiative",
      "count": 1
    },
    {
      "word": "imagination",
      "count": 1
    },
    {
      "word": "continuer",
      "count": 1
    },
    {
      "word": "activité",
      "count": 1
    },
    {
      "word": "profiter",
      "count": 1
    },
    {
      "word": "commune",
      "count": 1
    },
    {
      "word": "soutenir",
      "count": 1
    },
    {
      "word": "volonté",
      "count": 1
    },
    {
      "word": "accompagner",
      "count": 1
    },
    {
      "word": "dynamisme",
      "count": 1
    },
    {
      "word": "proposeron",
      "count": 1
    },
    {
      "word": "prochain",
      "count": 1
    },
    {
      "word": "conseil",
      "count": 1
    }
  ],
  "portrait": "default.svg",
  "name": "Virginie MALOLEPSZY",
  "mandates": [
    "Adjointe au maire"
  ],
  "groups": [
    "Majorité municipale : Douai au Cœur (Vivre Douai)"
  ],
  "groupsIds": [
    "douai-au-coeur-se"
  ],
  "locality": "Douai",
  "country": "France",
  "summary": {
    "sentences": {
      "mean": 7,
      "min": 7,
      "max": 7
    },
    "exclamations": {
      "mean": 1,
      "min": 1,
      "max": 1
    },
    "questions": {
      "mean": 0,
      "min": 0,
      "max": 0
    },
    "bolds": {
      "mean": 0,
      "min": 0,
      "max": 0
    },
    "caps": {
      "mean": 0,
      "min": 0,
      "max": 0
    },
    "sentiments": {
      "positive": {
        "mean": 1,
        "min": 1,
        "max": 1
      },
      "neutral": {
        "mean": 6,
        "min": 6,
        "max": 6
      },
      "negative": {
        "mean": 0,
        "min": 0,
        "max": 0
      }
    }
  }
}